{
  "created_at": "2026-07-16T08:18:25.696251+00:00",
  "csv": "loto7.csv",
  "decision": {
    "max_null_exceedance": 0.1,
    "max_pbo": 0.4,
    "passed": false,
    "reasons": [
      "null exceedance=0.450000",
      "PBO=0.350000"
    ]
  },
  "end_year": null,
  "kind": "loto7_null_strategy_league",
  "model": "loto7_best_model.json",
  "model_metrics": {
    "max_main_match": 5.0,
    "median_year_roi_percent": 18.693,
    "robust_score": 19.3268,
    "roi_excluding_top1_percent": 14.325,
    "roi_percent": 16.607
  },
  "model_percentile": 0.45,
  "notes": [
    "The model is compared with many deterministic null strategies under the same five-ticket cost.",
    "PBO is a CSCV-style diagnostic and not a proof of predictability."
  ],
  "null_distribution": {
    "robust_score_p50": 18.990134,
    "robust_score_p90": 22.42885,
    "robust_score_p95": 23.676975,
    "top1_removed_roi_p90": 18.335317,
    "top1_removed_roi_p95": 19.374008
  },
  "null_results": [
    {
      "max_main_match": 5.0,
      "median_year_roi_percent": 15.294118,
      "robust_score": 18.48722,
      "roi_excluding_top1_percent": 14.345238,
      "roi_percent": 16.607143,
      "simulation": 0,
      "strategy": "random"
    },
    {
      "max_main_match": 5.0,
      "median_year_roi_percent": 18.024691,
      "robust_score": 22.51907,
      "roi_excluding_top1_percent": 19.543651,
      "roi_percent": 21.607143,
      "simulation": 1,
      "strategy": "balanced"
    },
    {
      "max_main_match": 5.0,
      "median_year_roi_percent": 13.72549,
      "robust_score": 17.144666,
      "roi_excluding_top1_percent": 13.075397,
      "roi_percent": 14.503968,
      "simulation": 2,
      "strategy": "frequency"
    },
    {
      "max_main_match": 4.0,
      "median_year_roi_percent": 12.564103,
      "robust_score": 16.060668,
      "roi_excluding_top1_percent": 13.571429,
      "roi_percent": 14.22619,
      "simulation": 3,
      "strategy": "dormancy"
    },
    {
      "max_main_match": 5.0,
      "median_year_roi_percent": 14.901961,
      "robust_score": 19.421919,
      "roi_excluding_top1_percent": 15.952381,
      "roi_percent": 18.134921,
      "simulation": 4,
      "strategy": "recent"
    },
    {
      "max_main_match": 5.0,
      "median_year_roi_percent": 27.189542,
      "robust_score": 26.493814,
      "roi_excluding_top1_percent": 22.142857,
      "roi_percent": 24.166667,
      "simulation": 5,
      "strategy": "hybrid"
    },
    {
      "max_main_match": 4.0,
      "median_year_roi_percent": 15.163399,
      "robust_score": 17.109302,
      "roi_excluding_top1_percent": 14.166667,
      "roi_percent": 14.900794,
      "simulation": 6,
      "strategy": "random"
    },
    {
      "max_main_match": 5.0,
      "median_year_roi_percent": 19.102564,
      "robust_score": 20.538538,
      "roi_excluding_top1_percent": 15.972222,
      "roi_percent": 18.511905,
      "simulation": 7,
      "strategy": "balanced"
    },
    {
      "max_main_match": 5.0,
      "median_year_roi_percent": 13.974359,
      "robust_score": 20.406288,
      "roi_excluding_top1_percent": 17.777778,
      "roi_percent": 20.15873,
      "simulation": 8,
      "strategy": "frequency"
    },
    {
      "max_main_match": 4.0,
      "median_year_roi_percent": 14.248366,
      "robust_score": 16.614671,
      "roi_excluding_top1_percent": 13.789683,
      "roi_percent": 14.384921,
      "simulation": 9,
      "strategy": "dormancy"
    },
    {
      "max_main_match": 5.0,
      "median_year_roi_percent": 18.717949,
      "robust_score": 21.59417,
      "roi_excluding_top1_percent": 17.876984,
      "roi_percent": 19.84127,
      "simulation": 10,
      "strategy": "recent"
    },
    {
      "max_main_match": 5.0,
      "median_year_roi_percent": 14.509804,
      "robust_score": 19.513364,
      "roi_excluding_top1_percent": 16.170635,
      "roi_percent": 18.670635,
      "simulation": 11,
      "strategy": "hybrid"
    },
    {
      "max_main_match": 5.0,
      "median_year_roi_percent": 17.948718,
      "robust_score": 20.523886,
      "roi_excluding_top1_percent": 16.686508,
      "roi_percent": 17.956349,
      "simulation": 12,
      "strategy": "random"
    },
    {
      "max_main_match": 5.0,
      "median_year_roi_percent": 15.308642,
      "robust_score": 18.717041,
      "roi_excluding_top1_percent": 14.761905,
      "roi_percent": 16.72619,
      "simulation": 13,
      "strategy": "balanced"
    },
    {
      "max_main_match": 5.0,
      "median_year_roi_percent": 13.974359,
      "robust_score": 18.054106,
      "roi_excluding_top1_percent": 14.365079,
      "roi_percent": 15.853175,
      "simulation": 14,
      "strategy": "frequency"
    },
    {
      "max_main_match": 5.0,
      "median_year_roi_percent": 16.993464,
      "robust_score": 19.322771,
      "roi_excluding_top1_percent": 15.0,
      "roi_percent": 17.162698,
      "simulation": 15,
      "strategy": "dormancy"
    },
    {
      "max_main_match": 4.0,
      "median_year_roi_percent": 10.326797,
      "robust_score": 14.568803,
      "roi_excluding_top1_percent": 12.18254,
      "roi_percent": 12.638889,
      "simulation": 16,
      "strategy": "recent"
    },
    {
      "max_main_match": 5.0,
      "median_year_roi_percent": 13.08642,
      "robust_score": 16.859899,
      "roi_excluding_top1_percent": 12.896825,
      "roi_percent": 14.265873,
      "simulation": 17,
      "strategy": "hybrid"
    },
    {
      "max_main_match": 4.0,
      "median_year_roi_percent": 10.641026,
      "robust_score": 13.704899,
      "roi_excluding_top1_percent": 10.714286,
      "roi_percent": 11.25,
      "simulation": 18,
      "strategy": "random"
    },
    {
      "max_main_match": 5.0,
      "median_year_roi_percent": 14.487179,
      "robust_score": 18.002747,
      "roi_excluding_top1_percent": 14.047619,
      "roi_percent": 15.714286,
      "simulation": 19,
      "strategy": "balanced"
    },
    {
      "max_main_match": 5.0,
      "median_year_roi_percent": 12.435897,
      "robust_score": 15.9433,
      "roi_excluding_top1_percent": 11.56746,
      "roi_percent": 13.670635,
      "simulation": 20,
      "strategy": "frequency"
    },
    {
      "max_main_match": 5.0,
      "median_year_roi_percent": 16.20915,
      "robust_score": 19.242764,
      "roi_excluding_top1_percent": 15.416667,
      "roi_percent": 16.547619,
      "simulation": 21,
      "strategy": "dormancy"
    },
    {
      "max_main_match": 5.0,
      "median_year_roi_percent": 14.771242,
      "robust_score": 20.664041,
      "roi_excluding_top1_percent": 17.936508,
      "roi_percent": 20.019841,
      "simulation": 22,
      "strategy": "recent"
    },
    {
      "max_main_match": 5.0,
      "median_year_roi_percent": 18.169935,
      "robust_score": 20.068277,
      "roi_excluding_top1_percent": 15.813492,
      "roi_percent": 17.460317,
      "simulation": 23,
      "strategy": "hybrid"
    },
    {
      "max_main_match": 5.0,
      "median_year_roi_percent": 15.424837,
      "robust_score": 18.916725,
      "roi_excluding_top1_percent": 15.079365,
      "roi_percent": 16.805556,
      "simulation": 24,
      "strategy": "random"
    },
    {
      "max_main_match": 5.0,
      "median_year_roi_percent": 12.287582,
      "robust_score": 16.712768,
      "roi_excluding_top1_percent": 12.81746,
      "roi_percent": 14.880952,
      "simulation": 25,
      "strategy": "balanced"
    },
    {
      "max_main_match": 5.0,
      "median_year_roi_percent": 19.084967,
      "robust_score": 21.699813,
      "roi_excluding_top1_percent": 17.916667,
      "roi_percent": 19.801587,
      "simulation": 26,
      "strategy": "frequency"
    },
    {
      "max_main_match": 5.0,
      "median_year_roi_percent": 15.308642,
      "robust_score": 19.631724,
      "roi_excluding_top1_percent": 16.210317,
      "roi_percent": 17.996032,
      "simulation": 27,
      "strategy": "dormancy"
    },
    {
      "max_main_match": 5.0,
      "median_year_roi_percent": 17.124183,
      "robust_score": 21.246324,
      "roi_excluding_top1_percent": 17.936508,
      "roi_percent": 19.980159,
      "simulation": 28,
      "strategy": "recent"
    },
    {
      "max_main_match": 5.0,
      "median_year_roi_percent": 9.358974,
      "robust_score": 14.507402,
      "roi_excluding_top1_percent": 10.615079,
      "roi_percent": 12.400794,
      "simulation": 29,
      "strategy": "hybrid"
    },
    {
      "max_main_match": 5.0,
      "median_year_roi_percent": 17.820513,
      "robust_score": 19.236874,
      "roi_excluding_top1_percent": 14.68254,
      "roi_percent": 16.269841,
      "simulation": 30,
      "strategy": "random"
    },
    {
      "max_main_match": 6.0,
      "median_year_roi_percent": 14.074074,
      "robust_score": 44.635582,
      "roi_excluding_top1_percent": 12.936508,
      "roi_percent": 190.992063,
      "simulation": 31,
      "strategy": "balanced"
    },
    {
      "max_main_match": 5.0,
      "median_year_roi_percent": 11.410256,
      "robust_score": 16.979548,
      "roi_excluding_top1_percent": 13.551587,
      "roi_percent": 15.674603,
      "simulation": 32,
      "strategy": "frequency"
    },
    {
      "max_main_match": 5.0,
      "median_year_roi_percent": 12.592593,
      "robust_score": 17.371362,
      "roi_excluding_top1_percent": 13.690476,
      "roi_percent": 15.853175,
      "simulation": 33,
      "strategy": "dormancy"
    },
    {
      "max_main_match": 5.0,
      "median_year_roi_percent": 17.647059,
      "robust_score": 20.408789,
      "roi_excluding_top1_percent": 16.488095,
      "roi_percent": 18.353175,
      "simulation": 34,
      "strategy": "recent"
    },
    {
      "max_main_match": 5.0,
      "median_year_roi_percent": 12.810458,
      "robust_score": 18.221464,
      "roi_excluding_top1_percent": 14.960317,
      "roi_percent": 16.924603,
      "simulation": 35,
      "strategy": "hybrid"
    },
    {
      "max_main_match": 5.0,
      "median_year_roi_percent": 17.564103,
      "robust_score": 20.448565,
      "roi_excluding_top1_percent": 16.507937,
      "roi_percent": 18.690476,
      "simulation": 36,
      "strategy": "random"
    },
    {
      "max_main_match": 5.0,
      "median_year_roi_percent": 21.830065,
      "robust_score": 23.669818,
      "roi_excluding_top1_percent": 19.84127,
      "roi_percent": 21.944444,
      "simulation": 37,
      "strategy": "balanced"
    },
    {
      "max_main_match": 5.0,
      "median_year_roi_percent": 15.128205,
      "robust_score": 19.494353,
      "roi_excluding_top1_percent": 15.972222,
      "roi_percent": 18.174603,
      "simulation": 38,
      "strategy": "frequency"
    },
    {
      "max_main_match": 4.0,
      "median_year_roi_percent": 15.512821,
      "robust_score": 17.267094,
      "roi_excluding_top1_percent": 14.325397,
      "roi_percent": 14.84127,
      "simulation": 39,
      "strategy": "dormancy"
    },
    {
      "max_main_match": 5.0,
      "median_year_roi_percent": 14.615385,
      "robust_score": 18.336386,
      "roi_excluding_top1_percent": 14.484127,
      "roi_percent": 16.269841,
      "simulation": 40,
      "strategy": "recent"
    },
    {
      "max_main_match": 5.0,
      "median_year_roi_percent": 29.487179,
      "robust_score": 27.510684,
      "roi_excluding_top1_percent": 22.777778,
      "roi_percent": 25.0,
      "simulation": 41,
      "strategy": "hybrid"
    },
    {
      "max_main_match": 5.0,
      "median_year_roi_percent": 14.320988,
      "robust_score": 18.577271,
      "roi_excluding_top1_percent": 14.880952,
      "roi_percent": 17.043651,
      "simulation": 42,
      "strategy": "random"
    },
    {
      "max_main_match": 5.0,
      "median_year_roi_percent": 22.222222,
      "robust_score": 23.265873,
      "roi_excluding_top1_percent": 19.146825,
      "roi_percent": 20.912698,
      "simulation": 43,
      "strategy": "balanced"
    },
    {
      "max_main_match": 5.0,
      "median_year_roi_percent": 17.948718,
      "robust_score": 19.081426,
      "roi_excluding_top1_percent": 14.325397,
      "roi_percent": 16.210317,
      "simulation": 44,
      "strategy": "frequency"
    },
    {
      "max_main_match": 5.0,
      "median_year_roi_percent": 12.287582,
      "robust_score": 15.35761,
      "roi_excluding_top1_percent": 10.833333,
      "roi_percent": 12.460317,
      "simulation": 45,
      "strategy": "dormancy"
    },
    {
      "max_main_match": 4.0,
      "median_year_roi_percent": 15.424837,
      "robust_score": 17.028828,
      "roi_excluding_top1_percent": 13.988095,
      "roi_percent": 14.52381,
      "simulation": 46,
      "strategy": "recent"
    },
    {
      "max_main_match": 5.0,
      "median_year_roi_percent": 19.358974,
      "robust_score": 21.632402,
      "roi_excluding_top1_percent": 17.81746,
      "roi_percent": 19.22619,
      "simulation": 47,
      "strategy": "hybrid"
    },
    {
      "max_main_match": 5.0,
      "median_year_roi_percent": 17.037037,
      "robust_score": 19.011243,
      "roi_excluding_top1_percent": 14.742063,
      "roi_percent": 15.873016,
      "simulation": 48,
      "strategy": "random"
    },
    {
      "max_main_match": 5.0,
      "median_year_roi_percent": 19.358974,
      "robust_score": 20.481609,
      "roi_excluding_top1_percent": 16.111111,
      "roi_percent": 17.242063,
      "simulation": 49,
      "strategy": "balanced"
    },
    {
      "max_main_match": 5.0,
      "median_year_roi_percent": 14.379085,
      "robust_score": 18.600724,
      "roi_excluding_top1_percent": 15.059524,
      "roi_percent": 16.507937,
      "simulation": 50,
      "strategy": "frequency"
    },
    {
      "max_main_match": 5.0,
      "median_year_roi_percent": 16.993464,
      "robust_score": 19.559874,
      "roi_excluding_top1_percent": 15.218254,
      "roi_percent": 18.015873,
      "simulation": 51,
      "strategy": "dormancy"
    },
    {
      "max_main_match": 5.0,
      "median_year_roi_percent": 21.30719,
      "robust_score": 22.942869,
      "roi_excluding_top1_percent": 18.809524,
      "roi_percent": 21.40873,
      "simulation": 52,
      "strategy": "recent"
    },
    {
      "max_main_match": 5.0,
      "median_year_roi_percent": 15.03268,
      "robust_score": 18.004202,
      "roi_excluding_top1_percent": 13.90873,
      "roi_percent": 15.277778,
      "simulation": 53,
      "strategy": "hybrid"
    },
    {
      "max_main_match": 5.0,
      "median_year_roi_percent": 15.25641,
      "robust_score": 19.853785,
      "roi_excluding_top1_percent": 16.507937,
      "roi_percent": 18.571429,
      "simulation": 54,
      "strategy": "random"
    },
    {
      "max_main_match": 5.0,
      "median_year_roi_percent": 16.54321,
      "robust_score": 19.679453,
      "roi_excluding_top1_percent": 15.813492,
      "roi_percent": 17.579365,
      "simulation": 55,
      "strategy": "balanced"
    },
    {
      "max_main_match": 5.0,
      "median_year_roi_percent": 19.74359,
      "robust_score": 22.215659,
      "roi_excluding_top1_percent": 18.333333,
      "roi_percent": 20.753968,
      "simulation": 56,
      "strategy": "frequency"
    },
    {
      "max_main_match": 4.0,
      "median_year_roi_percent": 14.640523,
      "robust_score": 17.119456,
      "roi_excluding_top1_percent": 14.424603,
      "roi_percent": 14.980159,
      "simulation": 57,
      "strategy": "dormancy"
    },
    {
      "max_main_match": 5.0,
      "median_year_roi_percent": 16.470588,
      "robust_score": 18.225782,
      "roi_excluding_top1_percent": 13.59127,
      "roi_percent": 15.416667,
      "simulation": 58,
      "strategy": "recent"
    },
    {
      "max_main_match": 5.0,
      "median_year_roi_percent": 15.03268,
      "robust_score": 19.057773,
      "roi_excluding_top1_percent": 15.396825,
      "roi_percent": 17.34127,
      "simulation": 59,
      "strategy": "hybrid"
    },
    {
      "max_main_match": 5.0,
      "median_year_roi_percent": 11.633987,
      "robust_score": 16.617822,
      "roi_excluding_top1_percent": 13.055556,
      "roi_percent": 14.543651,
      "simulation": 60,
      "strategy": "random"
    },
    {
      "max_main_match": 5.0,
      "median_year_roi_percent": 13.333333,
      "robust_score": 17.772817,
      "roi_excluding_top1_percent": 14.146825,
      "roi_percent": 15.77381,
      "simulation": 61,
      "strategy": "balanced"
    },
    {
      "max_main_match": 5.0,
      "median_year_roi_percent": 14.358974,
      "robust_score": 18.210775,
      "roi_excluding_top1_percent": 14.444444,
      "roi_percent": 15.992063,
      "simulation": 62,
      "strategy": "frequency"
    },
    {
      "max_main_match": 5.0,
      "median_year_roi_percent": 15.163399,
      "robust_score": 17.119223,
      "roi_excluding_top1_percent": 12.400794,
      "roi_percent": 14.186508,
      "simulation": 63,
      "strategy": "dormancy"
    },
    {
      "max_main_match": 5.0,
      "median_year_roi_percent": 12.435897,
      "robust_score": 16.758776,
      "roi_excluding_top1_percent": 12.757937,
      "roi_percent": 15.138889,
      "simulation": 64,
      "strategy": "recent"
    },
    {
      "max_main_match": 5.0,
      "median_year_roi_percent": 19.506173,
      "robust_score": 21.091821,
      "roi_excluding_top1_percent": 16.746032,
      "roi_percent": 18.948413,
      "simulation": 65,
      "strategy": "hybrid"
    },
    {
      "max_main_match": 5.0,
      "median_year_roi_percent": 18.518519,
      "robust_score": 19.987765,
      "roi_excluding_top1_percent": 15.496032,
      "roi_percent": 17.400794,
      "simulation": 66,
      "strategy": "random"
    },
    {
      "max_main_match": 4.0,
      "median_year_roi_percent": 11.111111,
      "robust_score": 14.296627,
      "roi_excluding_top1_percent": 11.448413,
      "roi_percent": 11.964286,
      "simulation": 67,
      "strategy": "balanced"
    },
    {
      "max_main_match": 5.0,
      "median_year_roi_percent": 21.794872,
      "robust_score": 21.981456,
      "roi_excluding_top1_percent": 17.261905,
      "roi_percent": 19.345238,
      "simulation": 68,
      "strategy": "frequency"
    },
    {
      "max_main_match": 5.0,
      "median_year_roi_percent": 21.282051,
      "robust_score": 23.3721,
      "roi_excluding_top1_percent": 19.603175,
      "roi_percent": 21.666667,
      "simulation": 69,
      "strategy": "dormancy"
    },
    {
      "max_main_match": 4.0,
      "median_year_roi_percent": 13.071895,
      "robust_score": 15.791783,
      "roi_excluding_top1_percent": 12.97619,
      "roi_percent": 13.571429,
      "simulation": 70,
      "strategy": "recent"
    },
    {
      "max_main_match": 5.0,
      "median_year_roi_percent": 22.469136,
      "robust_score": 22.829586,
      "roi_excluding_top1_percent": 18.353175,
      "roi_percent": 20.238095,
      "simulation": 71,
      "strategy": "hybrid"
    },
    {
      "max_main_match": 5.0,
      "median_year_roi_percent": 17.692308,
      "robust_score": 21.778236,
      "roi_excluding_top1_percent": 18.531746,
      "roi_percent": 20.595238,
      "simulation": 72,
      "strategy": "random"
    },
    {
      "max_main_match": 4.0,
      "median_year_roi_percent": 17.051282,
      "robust_score": 17.663614,
      "roi_excluding_top1_percent": 14.325397,
      "roi_percent": 14.920635,
      "simulation": 73,
      "strategy": "balanced"
    },
    {
      "max_main_match": 5.0,
      "median_year_roi_percent": 13.076923,
      "robust_score": 17.305937,
      "roi_excluding_top1_percent": 13.472222,
      "roi_percent": 15.337302,
      "simulation": 74,
      "strategy": "frequency"
    },
    {
      "max_main_match": 5.0,
      "median_year_roi_percent": 17.948718,
      "robust_score": 19.224283,
      "roi_excluding_top1_percent": 14.563492,
      "roi_percent": 16.369048,
      "simulation": 75,
      "strategy": "dormancy"
    },
    {
      "max_main_match": 5.0,
      "median_year_roi_percent": 13.461538,
      "robust_score": 16.612408,
      "roi_excluding_top1_percent": 12.202381,
      "roi_percent": 14.305556,
      "simulation": 76,
      "strategy": "recent"
    },
    {
      "max_main_match": 5.0,
      "median_year_roi_percent": 18.431373,
      "robust_score": 21.526494,
      "roi_excluding_top1_percent": 17.896825,
      "roi_percent": 19.801587,
      "simulation": 77,
      "strategy": "hybrid"
    },
    {
      "max_main_match": 5.0,
      "median_year_roi_percent": 14.320988,
      "robust_score": 18.149691,
      "roi_excluding_top1_percent": 14.365079,
      "roi_percent": 15.912698,
      "simulation": 78,
      "strategy": "random"
    },
    {
      "max_main_match": 6.0,
      "median_year_roi_percent": 12.179487,
      "robust_score": 40.155983,
      "roi_excluding_top1_percent": 14.603175,
      "roi_percent": 158.730159,
      "simulation": 79,
      "strategy": "balanced"
    },
    {
      "max_main_match": 5.0,
      "median_year_roi_percent": 17.254902,
      "robust_score": 20.915908,
      "roi_excluding_top1_percent": 17.400794,
      "roi_percent": 19.345238,
      "simulation": 80,
      "strategy": "frequency"
    },
    {
      "max_main_match": 5.0,
      "median_year_roi_percent": 16.20915,
      "robust_score": 21.444153,
      "roi_excluding_top1_percent": 18.551587,
      "roi_percent": 20.77381,
      "simulation": 81,
      "strategy": "dormancy"
    },
    {
      "max_main_match": 5.0,
      "median_year_roi_percent": 18.69281,
      "robust_score": 21.493639,
      "roi_excluding_top1_percent": 17.777778,
      "roi_percent": 19.543651,
      "simulation": 82,
      "strategy": "recent"
    },
    {
      "max_main_match": 5.0,
      "median_year_roi_percent": 13.333333,
      "robust_score": 16.986111,
      "roi_excluding_top1_percent": 12.876984,
      "roi_percent": 14.761905,
      "simulation": 83,
      "strategy": "hybrid"
    },
    {
      "max_main_match": 5.0,
      "median_year_roi_percent": 12.051282,
      "robust_score": 17.806471,
      "roi_excluding_top1_percent": 14.563492,
      "roi_percent": 16.746032,
      "simulation": 84,
      "strategy": "random"
    },
    {
      "max_main_match": 5.0,
      "median_year_roi_percent": 16.666667,
      "robust_score": 20.406746,
      "roi_excluding_top1_percent": 16.825397,
      "roi_percent": 18.849206,
      "simulation": 85,
      "strategy": "balanced"
    },
    {
      "max_main_match": 5.0,
      "median_year_roi_percent": 15.897436,
      "robust_score": 19.59043,
      "roi_excluding_top1_percent": 15.77381,
      "roi_percent": 18.194444,
      "simulation": 86,
      "strategy": "frequency"
    },
    {
      "max_main_match": 5.0,
      "median_year_roi_percent": 13.071895,
      "robust_score": 16.874125,
      "roi_excluding_top1_percent": 12.777778,
      "roi_percent": 14.781746,
      "simulation": 87,
      "strategy": "dormancy"
    },
    {
      "max_main_match": 5.0,
      "median_year_roi_percent": 17.51634,
      "robust_score": 18.08841,
      "roi_excluding_top1_percent": 12.876984,
      "roi_percent": 15.138889,
      "simulation": 88,
      "strategy": "recent"
    },
    {
      "max_main_match": 4.0,
      "median_year_roi_percent": 17.820513,
      "robust_score": 19.765644,
      "roi_excluding_top1_percent": 17.281746,
      "roi_percent": 17.797619,
      "simulation": 89,
      "strategy": "hybrid"
    },
    {
      "max_main_match": 5.0,
      "median_year_roi_percent": 16.025641,
      "robust_score": 18.302045,
      "roi_excluding_top1_percent": 13.888889,
      "roi_percent": 15.674603,
      "simulation": 90,
      "strategy": "random"
    },
    {
      "max_main_match": 4.0,
      "median_year_roi_percent": 14.640523,
      "robust_score": 16.665091,
      "roi_excluding_top1_percent": 13.730159,
      "roi_percent": 14.265873,
      "simulation": 91,
      "strategy": "balanced"
    },
    {
      "max_main_match": 5.0,
      "median_year_roi_percent": 14.814815,
      "robust_score": 17.933862,
      "roi_excluding_top1_percent": 13.769841,
      "roi_percent": 15.634921,
      "simulation": 92,
      "strategy": "frequency"
    },
    {
      "max_main_match": 5.0,
      "median_year_roi_percent": 15.128205,
      "robust_score": 18.539988,
      "roi_excluding_top1_percent": 14.623016,
      "roi_percent": 16.309524,
      "simulation": 93,
      "strategy": "dormancy"
    },
    {
      "max_main_match": 5.0,
      "median_year_roi_percent": 21.025641,
      "robust_score": 23.812958,
      "roi_excluding_top1_percent": 20.47619,
      "roi_percent": 22.123016,
      "simulation": 94,
      "strategy": "recent"
    },
    {
      "max_main_match": 5.0,
      "median_year_roi_percent": 17.124183,
      "robust_score": 20.036006,
      "roi_excluding_top1_percent": 16.170635,
      "roi_percent": 17.797619,
      "simulation": 95,
      "strategy": "hybrid"
    },
    {
      "max_main_match": 5.0,
      "median_year_roi_percent": 15.802469,
      "robust_score": 19.371252,
      "roi_excluding_top1_percent": 15.496032,
      "roi_percent": 17.81746,
      "simulation": 96,
      "strategy": "random"
    },
    {
      "max_main_match": 5.0,
      "median_year_roi_percent": 15.769231,
      "robust_score": 19.855006,
      "roi_excluding_top1_percent": 16.349206,
      "roi_percent": 18.253968,
      "simulation": 97,
      "strategy": "balanced"
    },
    {
      "max_main_match": 5.0,
      "median_year_roi_percent": 14.230769,
      "robust_score": 17.920788,
      "roi_excluding_top1_percent": 13.928571,
      "roi_percent": 15.992063,
      "simulation": 98,
      "strategy": "frequency"
    },
    {
      "max_main_match": 5.0,
      "median_year_roi_percent": 12.287582,
      "robust_score": 16.822887,
      "roi_excluding_top1_percent": 12.996032,
      "roi_percent": 15.019841,
      "simulation": 99,
      "strategy": "dormancy"
    },
    {
      "max_main_match": 5.0,
      "median_year_roi_percent": 16.993464,
      "robust_score": 19.662056,
      "roi_excluding_top1_percent": 15.595238,
      "roi_percent": 17.440476,
      "simulation": 100,
      "strategy": "recent"
    },
    {
      "max_main_match": 5.0,
      "median_year_roi_percent": 13.986928,
      "robust_score": 17.737803,
      "roi_excluding_top1_percent": 13.809524,
      "roi_percent": 15.575397,
      "simulation": 101,
      "strategy": "hybrid"
    },
    {
      "max_main_match": 5.0,
      "median_year_roi_percent": 13.08642,
      "robust_score": 18.969026,
      "roi_excluding_top1_percent": 16.09127,
      "roi_percent": 17.678571,
      "simulation": 102,
      "strategy": "random"
    },
    {
      "max_main_match": 5.0,
      "median_year_roi_percent": 23.45679,
      "robust_score": 21.849317,
      "roi_excluding_top1_percent": 16.428571,
      "roi_percent": 18.472222,
      "simulation": 103,
      "strategy": "balanced"
    },
    {
      "max_main_match": 5.0,
      "median_year_roi_percent": 16.54321,
      "robust_score": 18.820326,
      "roi_excluding_top1_percent": 14.464286,
      "roi_percent": 16.349206,
      "simulation": 104,
      "strategy": "frequency"
    },
    {
      "max_main_match": 5.0,
      "median_year_roi_percent": 12.051282,
      "robust_score": 15.544567,
      "roi_excluding_top1_percent": 11.230159,
      "roi_percent": 12.777778,
      "simulation": 105,
      "strategy": "dormancy"
    },
    {
      "max_main_match": 5.0,
      "median_year_roi_percent": 18.69281,
      "robust_score": 21.671218,
      "roi_excluding_top1_percent": 17.936508,
      "roi_percent": 20.198413,
      "simulation": 106,
      "strategy": "recent"
    },
    {
      "max_main_match": 5.0,
      "median_year_roi_percent": 16.470588,
      "robust_score": 19.887488,
      "roi_excluding_top1_percent": 16.111111,
      "roi_percent": 18.095238,
      "simulation": 107,
      "strategy": "hybrid"
    },
    {
      "max_main_match": 5.0,
      "median_year_roi_percent": 16.790123,
      "robust_score": 18.455467,
      "roi_excluding_top1_percent": 13.849206,
      "roi_percent": 15.555556,
      "simulation": 108,
      "strategy": "random"
    },
    {
      "max_main_match": 5.0,
      "median_year_roi_percent": 18.076923,
      "robust_score": 19.894231,
      "roi_excluding_top1_percent": 15.595238,
      "roi_percent": 17.18254,
      "simulation": 109,
      "strategy": "balanced"
    },
    {
      "max_main_match": 5.0,
      "median_year_roi_percent": 16.339869,
      "robust_score": 20.017507,
      "roi_excluding_top1_percent": 16.388889,
      "roi_percent": 18.253968,
      "simulation": 110,
      "strategy": "frequency"
    },
    {
      "max_main_match": 5.0,
      "median_year_roi_percent": 15.308642,
      "robust_score": 16.925375,
      "roi_excluding_top1_percent": 11.904762,
      "roi_percent": 14.305556,
      "simulation": 111,
      "strategy": "dormancy"
    },
    {
      "max_main_match": 5.0,
      "median_year_roi_percent": 10.897436,
      "robust_score": 16.295788,
      "roi_excluding_top1_percent": 12.857143,
      "roi_percent": 14.285714,
      "simulation": 112,
      "strategy": "recent"
    },
    {
      "max_main_match": 5.0,
      "median_year_roi_percent": 11.282051,
      "robust_score": 14.610195,
      "roi_excluding_top1_percent": 10.198413,
      "roi_percent": 11.269841,
      "simulation": 113,
      "strategy": "hybrid"
    },
    {
      "max_main_match": 5.0,
      "median_year_roi_percent": 12.820513,
      "robust_score": 18.409493,
      "roi_excluding_top1_percent": 15.277778,
      "roi_percent": 17.103175,
      "simulation": 114,
      "strategy": "random"
    },
    {
      "max_main_match": 5.0,
      "median_year_roi_percent": 20.522876,
      "robust_score": 21.988854,
      "roi_excluding_top1_percent": 17.81746,
      "roi_percent": 19.662698,
      "simulation": 115,
      "strategy": "balanced"
    },
    {
      "max_main_match": 5.0,
      "median_year_roi_percent": 19.607843,
      "robust_score": 22.048786,
      "roi_excluding_top1_percent": 18.234127,
      "roi_percent": 20.198413,
      "simulation": 116,
      "strategy": "frequency"
    },
    {
      "max_main_match": 5.0,
      "median_year_roi_percent": 18.589744,
      "robust_score": 20.749618,
      "roi_excluding_top1_percent": 16.686508,
      "roi_percent": 18.392857,
      "simulation": 117,
      "strategy": "dormancy"
    },
    {
      "max_main_match": 5.0,
      "median_year_roi_percent": 15.384615,
      "robust_score": 19.758852,
      "roi_excluding_top1_percent": 16.468254,
      "roi_percent": 17.857143,
      "simulation": 118,
      "strategy": "recent"
    },
    {
      "max_main_match": 4.0,
      "median_year_roi_percent": 16.470588,
      "robust_score": 18.53729,
      "roi_excluding_top1_percent": 15.892857,
      "roi_percent": 16.488095,
      "simulation": 119,
      "strategy": "hybrid"
    },
    {
      "max_main_match": 4.0,
      "median_year_roi_percent": 13.076923,
      "robust_score": 15.611493,
      "roi_excluding_top1_percent": 12.738095,
      "roi_percent": 13.154762,
      "simulation": 120,
      "strategy": "random"
    },
    {
      "max_main_match": 5.0,
      "median_year_roi_percent": 17.254902,
      "robust_score": 22.043884,
      "roi_excluding_top1_percent": 19.126984,
      "roi_percent": 21.111111,
      "simulation": 121,
      "strategy": "balanced"
    },
    {
      "max_main_match": 5.0,
      "median_year_roi_percent": 18.431373,
      "robust_score": 23.083042,
      "roi_excluding_top1_percent": 20.277778,
      "roi_percent": 22.242063,
      "simulation": 122,
      "strategy": "frequency"
    },
    {
      "max_main_match": 6.0,
      "median_year_roi_percent": 18.846154,
      "robust_score": 36.005189,
      "roi_excluding_top1_percent": 18.194444,
      "roi_percent": 107.97619,
      "simulation": 123,
      "strategy": "dormancy"
    },
    {
      "max_main_match": 4.0,
      "median_year_roi_percent": 15.0,
      "robust_score": 16.384921,
      "roi_excluding_top1_percent": 13.174603,
      "roi_percent": 13.650794,
      "simulation": 124,
      "strategy": "recent"
    },
    {
      "max_main_match": 5.0,
      "median_year_roi_percent": 12.679739,
      "robust_score": 16.572712,
      "roi_excluding_top1_percent": 12.519841,
      "roi_percent": 14.285714,
      "simulation": 125,
      "strategy": "hybrid"
    },
    {
      "max_main_match": 5.0,
      "median_year_roi_percent": 13.72549,
      "robust_score": 17.841095,
      "roi_excluding_top1_percent": 14.146825,
      "roi_percent": 15.575397,
      "simulation": 126,
      "strategy": "random"
    },
    {
      "max_main_match": 5.0,
      "median_year_roi_percent": 14.615385,
      "robust_score": 17.741148,
      "roi_excluding_top1_percent": 13.59127,
      "roi_percent": 15.277778,
      "simulation": 127,
      "strategy": "balanced"
    },
    {
      "max_main_match": 5.0,
      "median_year_roi_percent": 13.974359,
      "robust_score": 17.935058,
      "roi_excluding_top1_percent": 14.06746,
      "roi_percent": 16.051587,
      "simulation": 128,
      "strategy": "frequency"
    },
    {
      "max_main_match": 5.0,
      "median_year_roi_percent": 17.254902,
      "robust_score": 18.712535,
      "roi_excluding_top1_percent": 13.928571,
      "roi_percent": 16.230159,
      "simulation": 129,
      "strategy": "dormancy"
    },
    {
      "max_main_match": 5.0,
      "median_year_roi_percent": 15.294118,
      "robust_score": 20.17472,
      "roi_excluding_top1_percent": 17.083333,
      "roi_percent": 18.730159,
      "simulation": 130,
      "strategy": "recent"
    },
    {
      "max_main_match": 5.0,
      "median_year_roi_percent": 16.538462,
      "robust_score": 19.368742,
      "roi_excluding_top1_percent": 15.456349,
      "roi_percent": 16.706349,
      "simulation": 131,
      "strategy": "hybrid"
    },
    {
      "max_main_match": 5.0,
      "median_year_roi_percent": 13.333333,
      "robust_score": 19.578373,
      "roi_excluding_top1_percent": 16.746032,
      "roi_percent": 19.146825,
      "simulation": 132,
      "strategy": "random"
    },
    {
      "max_main_match": 5.0,
      "median_year_roi_percent": 12.810458,
      "robust_score": 17.975432,
      "roi_excluding_top1_percent": 14.68254,
      "roi_percent": 16.210317,
      "simulation": 133,
      "strategy": "balanced"
    },
    {
      "max_main_match": 4.0,
      "median_year_roi_percent": 15.0,
      "robust_score": 18.259921,
      "roi_excluding_top1_percent": 16.031746,
      "roi_percent": 16.626984,
      "simulation": 134,
      "strategy": "frequency"
    },
    {
      "max_main_match": 5.0,
      "median_year_roi_percent": 14.248366,
      "robust_score": 18.421218,
      "roi_excluding_top1_percent": 14.801587,
      "roi_percent": 16.388889,
      "simulation": 135,
      "strategy": "dormancy"
    },
    {
      "max_main_match": 5.0,
      "median_year_roi_percent": 14.379085,
      "robust_score": 18.140406,
      "roi_excluding_top1_percent": 14.365079,
      "roi_percent": 15.753968,
      "simulation": 136,
      "strategy": "recent"
    },
    {
      "max_main_match": 5.0,
      "median_year_roi_percent": 18.717949,
      "robust_score": 18.56044,
      "roi_excluding_top1_percent": 13.154762,
      "roi_percent": 15.357143,
      "simulation": 137,
      "strategy": "hybrid"
    },
    {
      "max_main_match": 4.0,
      "median_year_roi_percent": 13.589744,
      "robust_score": 16.83196,
      "roi_excluding_top1_percent": 14.404762,
      "roi_percent": 14.880952,
      "simulation": 138,
      "strategy": "random"
    },
    {
      "max_main_match": 5.0,
      "median_year_roi_percent": 18.562092,
      "robust_score": 21.439134,
      "roi_excluding_top1_percent": 17.698413,
      "roi_percent": 19.662698,
      "simulation": 139,
      "strategy": "balanced"
    },
    {
      "max_main_match": 5.0,
      "median_year_roi_percent": 14.615385,
      "robust_score": 19.715354,
      "roi_excluding_top1_percent": 16.587302,
      "roi_percent": 18.452381,
      "simulation": 140,
      "strategy": "frequency"
    },
    {
      "max_main_match": 5.0,
      "median_year_roi_percent": 10.980392,
      "robust_score": 14.700455,
      "roi_excluding_top1_percent": 10.297619,
      "roi_percent": 12.043651,
      "simulation": 141,
      "strategy": "dormancy"
    },
    {
      "max_main_match": 5.0,
      "median_year_roi_percent": 16.20915,
      "robust_score": 18.939192,
      "roi_excluding_top1_percent": 14.940476,
      "roi_percent": 16.111111,
      "simulation": 142,
      "strategy": "recent"
    },
    {
      "max_main_match": 5.0,
      "median_year_roi_percent": 13.202614,
      "robust_score": 18.665733,
      "roi_excluding_top1_percent": 15.396825,
      "roi_percent": 17.777778,
      "simulation": 143,
      "strategy": "hybrid"
    },
    {
      "max_main_match": 5.0,
      "median_year_roi_percent": 18.954248,
      "robust_score": 22.620507,
      "roi_excluding_top1_percent": 19.365079,
      "roi_percent": 21.329365,
      "simulation": 144,
      "strategy": "random"
    },
    {
      "max_main_match": 5.0,
      "median_year_roi_percent": 17.179487,
      "robust_score": 20.153999,
      "roi_excluding_top1_percent": 16.289683,
      "roi_percent": 18.095238,
      "simulation": 145,
      "strategy": "balanced"
    },
    {
      "max_main_match": 5.0,
      "median_year_roi_percent": 16.601307,
      "robust_score": 20.070962,
      "roi_excluding_top1_percent": 16.329365,
      "roi_percent": 18.373016,
      "simulation": 146,
      "strategy": "frequency"
    },
    {
      "max_main_match": 5.0,
      "median_year_roi_percent": 19.607843,
      "robust_score": 22.418826,
      "roi_excluding_top1_percent": 18.789683,
      "roi_percent": 20.813492,
      "simulation": 147,
      "strategy": "dormancy"
    },
    {
      "max_main_match": 5.0,
      "median_year_roi_percent": 12.345679,
      "robust_score": 16.589396,
      "roi_excluding_top1_percent": 12.857143,
      "roi_percent": 13.829365,
      "simulation": 148,
      "strategy": "recent"
    },
    {
      "max_main_match": 5.0,
      "median_year_roi_percent": 16.666667,
      "robust_score": 20.943452,
      "roi_excluding_top1_percent": 17.559524,
      "roi_percent": 19.980159,
      "simulation": 149,
      "strategy": "hybrid"
    },
    {
      "max_main_match": 4.0,
      "median_year_roi_percent": 12.679739,
      "robust_score": 16.47549,
      "roi_excluding_top1_percent": 14.206349,
      "roi_percent": 14.68254,
      "simulation": 150,
      "strategy": "random"
    },
    {
      "max_main_match": 4.0,
      "median_year_roi_percent": 10.0,
      "robust_score": 13.713294,
      "roi_excluding_top1_percent": 10.93254,
      "roi_percent": 11.646825,
      "simulation": 151,
      "strategy": "balanced"
    },
    {
      "max_main_match": 5.0,
      "median_year_roi_percent": 14.901961,
      "robust_score": 17.251284,
      "roi_excluding_top1_percent": 12.65873,
      "roi_percent": 14.642857,
      "simulation": 152,
      "strategy": "frequency"
    },
    {
      "max_main_match": 5.0,
      "median_year_roi_percent": 18.431373,
      "robust_score": 19.706057,
      "roi_excluding_top1_percent": 15.238095,
      "roi_percent": 16.527778,
      "simulation": 153,
      "strategy": "dormancy"
    },
    {
      "max_main_match": 4.0,
      "median_year_roi_percent": 11.923077,
      "robust_score": 14.584936,
      "roi_excluding_top1_percent": 11.607143,
      "roi_percent": 12.003968,
      "simulation": 154,
      "strategy": "recent"
    },
    {
      "max_main_match": 4.0,
      "median_year_roi_percent": 13.846154,
      "robust_score": 16.920864,
      "roi_excluding_top1_percent": 14.424603,
      "roi_percent": 14.980159,
      "simulation": 155,
      "strategy": "hybrid"
    },
    {
      "max_main_match": 5.0,
      "median_year_roi_percent": 15.0,
      "robust_score": 17.189484,
      "roi_excluding_top1_percent": 12.65873,
      "roi_percent": 14.06746,
      "simulation": 156,
      "strategy": "random"
    },
    {
      "max_main_match": 5.0,
      "median_year_roi_percent": 15.555556,
      "robust_score": 19.268849,
      "roi_excluding_top1_percent": 15.634921,
      "roi_percent": 17.083333,
      "simulation": 157,
      "strategy": "balanced"
    },
    {
      "max_main_match": 5.0,
      "median_year_roi_percent": 21.666667,
      "robust_score": 24.242063,
      "roi_excluding_top1_percent": 20.734127,
      "roi_percent": 23.055556,
      "simulation": 158,
      "strategy": "frequency"
    },
    {
      "max_main_match": 5.0,
      "median_year_roi_percent": 20.130719,
      "robust_score": 21.807481,
      "roi_excluding_top1_percent": 17.579365,
      "roi_percent": 19.900794,
      "simulation": 159,
      "strategy": "dormancy"
    },
    {
      "max_main_match": 5.0,
      "median_year_roi_percent": 16.862745,
      "robust_score": 19.87144,
      "roi_excluding_top1_percent": 16.09127,
      "roi_percent": 17.400794,
      "simulation": 160,
      "strategy": "recent"
    },
    {
      "max_main_match": 5.0,
      "median_year_roi_percent": 23.974359,
      "robust_score": 25.292201,
      "roi_excluding_top1_percent": 21.507937,
      "roi_percent": 23.630952,
      "simulation": 161,
      "strategy": "hybrid"
    },
    {
      "max_main_match": 4.0,
      "median_year_roi_percent": 17.948718,
      "robust_score": 18.21833,
      "roi_excluding_top1_percent": 14.861111,
      "roi_percent": 15.337302,
      "simulation": 162,
      "strategy": "random"
    },
    {
      "max_main_match": 5.0,
      "median_year_roi_percent": 17.124183,
      "robust_score": 20.400093,
      "roi_excluding_top1_percent": 16.666667,
      "roi_percent": 18.571429,
      "simulation": 163,
      "strategy": "balanced"
    },
    {
      "max_main_match": 5.0,
      "median_year_roi_percent": 18.039216,
      "robust_score": 19.163574,
      "roi_excluding_top1_percent": 14.384921,
      "roi_percent": 16.40873,
      "simulation": 164,
      "strategy": "frequency"
    },
    {
      "max_main_match": 5.0,
      "median_year_roi_percent": 22.948718,
      "robust_score": 23.376068,
      "roi_excluding_top1_percent": 19.027778,
      "roi_percent": 20.833333,
      "simulation": 165,
      "strategy": "dormancy"
    },
    {
      "max_main_match": 4.0,
      "median_year_roi_percent": 7.948718,
      "robust_score": 11.904838,
      "roi_excluding_top1_percent": 8.948413,
      "roi_percent": 9.623016,
      "simulation": 166,
      "strategy": "recent"
    },
    {
      "max_main_match": 4.0,
      "median_year_roi_percent": 11.410256,
      "robust_score": 13.987485,
      "roi_excluding_top1_percent": 10.853175,
      "roi_percent": 11.388889,
      "simulation": 167,
      "strategy": "hybrid"
    },
    {
      "max_main_match": 4.0,
      "median_year_roi_percent": 14.074074,
      "robust_score": 17.016534,
      "roi_excluding_top1_percent": 14.484127,
      "roi_percent": 15.039683,
      "simulation": 168,
      "strategy": "random"
    },
    {
      "max_main_match": 5.0,
      "median_year_roi_percent": 18.333333,
      "robust_score": 19.647817,
      "roi_excluding_top1_percent": 14.980159,
      "roi_percent": 17.162698,
      "simulation": 169,
      "strategy": "balanced"
    },
    {
      "max_main_match": 6.0,
      "median_year_roi_percent": 19.869281,
      "robust_score": 59.569503,
      "roi_excluding_top1_percent": 17.936508,
      "roi_percent": 264.22619,
      "simulation": 170,
      "strategy": "frequency"
    },
    {
      "max_main_match": 5.0,
      "median_year_roi_percent": 12.179487,
      "robust_score": 16.177808,
      "roi_excluding_top1_percent": 12.123016,
      "roi_percent": 13.809524,
      "simulation": 171,
      "strategy": "dormancy"
    },
    {
      "max_main_match": 5.0,
      "median_year_roi_percent": 16.410256,
      "robust_score": 17.912088,
      "roi_excluding_top1_percent": 13.095238,
      "roi_percent": 15.079365,
      "simulation": 172,
      "strategy": "recent"
    },
    {
      "max_main_match": 4.0,
      "median_year_roi_percent": 14.487179,
      "robust_score": 16.919414,
      "roi_excluding_top1_percent": 14.166667,
      "roi_percent": 14.761905,
      "simulation": 173,
      "strategy": "hybrid"
    },
    {
      "max_main_match": 5.0,
      "median_year_roi_percent": 14.509804,
      "robust_score": 17.728641,
      "roi_excluding_top1_percent": 13.571429,
      "roi_percent": 15.436508,
      "simulation": 174,
      "strategy": "random"
    },
    {
      "max_main_match": 5.0,
      "median_year_roi_percent": 16.410256,
      "robust_score": 20.229548,
      "roi_excluding_top1_percent": 16.706349,
      "roi_percent": 18.492063,
      "simulation": 175,
      "strategy": "balanced"
    },
    {
      "max_main_match": 5.0,
      "median_year_roi_percent": 15.555556,
      "robust_score": 20.529762,
      "roi_excluding_top1_percent": 17.400794,
      "roi_percent": 19.603175,
      "simulation": 176,
      "strategy": "frequency"
    },
    {
      "max_main_match": 5.0,
      "median_year_roi_percent": 17.51634,
      "robust_score": 19.885037,
      "roi_excluding_top1_percent": 15.714286,
      "roi_percent": 17.65873,
      "simulation": 177,
      "strategy": "dormancy"
    },
    {
      "max_main_match": 5.0,
      "median_year_roi_percent": 15.308642,
      "robust_score": 18.007716,
      "roi_excluding_top1_percent": 13.611111,
      "roi_percent": 15.833333,
      "simulation": 178,
      "strategy": "recent"
    },
    {
      "max_main_match": 5.0,
      "median_year_roi_percent": 16.993464,
      "robust_score": 20.481501,
      "roi_excluding_top1_percent": 16.865079,
      "roi_percent": 18.670635,
      "simulation": 179,
      "strategy": "hybrid"
    }
  ],
  "null_simulations": 180,
  "pbo": 0.35,
  "pbo_detail": {
    "block_count": 6,
    "combinations": 20,
    "median_oos_rank_logit": -0.357449,
    "pbo": 0.35
  },
  "start_year": 2020,
  "strategy_types": [
    "random",
    "balanced",
    "frequency",
    "dormancy",
    "recent",
    "hybrid"
  ],
  "target_draws": 336
}
