{
  "baseline": {
    "model_id": "g070_0070_3390",
    "path": "outputs/recent_era/recent_era_baseline_before_run.json",
    "recent": {
      "grade_hit_count": 64,
      "high_grade_hit_count": 4,
      "max_bonus_match": 2,
      "max_main_match": 6,
      "missing_prize_draw_count": 0,
      "profit": -41700,
      "rank_counts": {
        "1等": 0,
        "2等": 0,
        "3等": 1,
        "4等": 3,
        "5等": 23,
        "6等": 37,
        "外れ": 1621
      },
      "roi": 0.917507,
      "roi_percent": 91.751,
      "target_draws": 337,
      "total_cost": 505500,
      "total_payout": 463800,
      "total_tickets": 1685
    }
  },
  "best_model_after_guard": "outputs/recent_era/recent_era_guarded_candidate_model.json",
  "candidate": {
    "model_id": "g136_0136_7803",
    "path": "outputs/recent_era/recent_era_candidate_model.json",
    "recent": {
      "grade_hit_count": 50,
      "high_grade_hit_count": 2,
      "max_bonus_match": 2,
      "max_main_match": 5,
      "missing_prize_draw_count": 0,
      "profit": -437300,
      "rank_counts": {
        "1等": 0,
        "2等": 0,
        "3等": 0,
        "4等": 2,
        "5等": 25,
        "6等": 23,
        "外れ": 1635
      },
      "roi": 0.134916,
      "roi_percent": 13.492,
      "target_draws": 337,
      "total_cost": 505500,
      "total_payout": 68200,
      "total_tickets": 1685
    }
  },
  "created_at": "2026-07-24T08:22:05.802264+00:00",
  "csv": "loto7.csv",
  "decision": {
    "accepted": false,
    "reasons": [
      "recent roi floor ok: 13.492% >= 8.000%"
    ],
    "restore_on_fail": true,
    "restored_baseline": true,
    "same_model": false,
    "thresholds": {
      "allow_recent_high_grade_drop": false,
      "min_recent_payout_roi_percent": 8.0,
      "min_recent_profit_delta": 0,
      "min_recent_roi_delta_percent": 0.0
    },
    "warnings": [
      "recent roi dropped: delta=-78.259pt < 0.000pt",
      "recent profit dropped: delta=-395600 < 0",
      "recent high-grade dropped: delta=-2"
    ]
  },
  "kind": "loto7_recent_era_dedicated_guard",
  "notes": [
    "This guard intentionally ignores full-period ROI.",
    "Recent Era dedicated models are used only for Recent Era prediction slots.",
    "This does not guarantee lottery winnings or profit."
  ],
  "purchase_count": 5,
  "recent_start_year": 2020,
  "recent_target_draws_total": 337,
  "unit_cost": 300
}
